bitcointx/__init__.py
bitcointx/base58.py
bitcointx/bech32.py
bitcointx/py.typed
bitcointx/rpc.py
bitcointx/segwit_addr.py
bitcointx/signmessage.py
bitcointx/util.py
bitcointx/wallet.py
bitcointx/core/__init__.py
bitcointx/core/_bignum.py
bitcointx/core/_ripemd160.py
bitcointx/core/bitcoinconsensus.py
bitcointx/core/ecdasig_parse_der_lax.py
bitcointx/core/key.py
bitcointx/core/psbt.py
bitcointx/core/script.py
bitcointx/core/scripteval.py
bitcointx/core/secp256k1.py
bitcointx/core/serialize.py
bitcointx/core/sha256.py
bitcointx/tests/__init__.py
bitcointx/tests/test_async_and_threading.py
bitcointx/tests/test_base58.py
bitcointx/tests/test_bech32.py
bitcointx/tests/test_core.py
bitcointx/tests/test_hd_keys.py
bitcointx/tests/test_imports.py
bitcointx/tests/test_key.py
bitcointx/tests/test_keystore.py
bitcointx/tests/test_load_secp256k1.py
bitcointx/tests/test_psbt.py
bitcointx/tests/test_ripemd160.py
bitcointx/tests/test_rpc.py
bitcointx/tests/test_script.py
bitcointx/tests/test_scripteval.py
bitcointx/tests/test_segwit.py
bitcointx/tests/test_serialize.py
bitcointx/tests/test_sha256.py
bitcointx/tests/test_signmessage.py
bitcointx/tests/test_transactions.py
bitcointx/tests/test_wallet.py
python_bitcointx-1.1.5.dist-info/LICENSE
python_bitcointx-1.1.5.dist-info/METADATA
python_bitcointx-1.1.5.dist-info/WHEEL
python_bitcointx-1.1.5.dist-info/top_level.txt
python_bitcointx-1.1.5.dist-info/RECORD
