Metadata-Version: 2.1
Name: python-bitcointx
Version: 1.1.5
Summary: A library for handling Bitcoin transactions and associated data
Home-page: https://github.com/Simplexum/python-bitcointx
Keywords: bitcoin
Classifier: Programming Language :: Python :: 3.7
Classifier: Programming Language :: Python :: 3.8
Classifier: Programming Language :: Python :: 3.9
Classifier: Programming Language :: Python :: 3.10
Classifier: Programming Language :: Python :: 3.11
Classifier: License :: OSI Approved :: GNU Lesser General Public License v3 or later (LGPLv3+)
Requires-Python: >=3.7
License-File: LICENSE
